blockrun_llm/__init__.py
blockrun_llm/client.py
blockrun_llm/image.py
blockrun_llm/types.py
blockrun_llm/validation.py
blockrun_llm/wallet.py
blockrun_llm/x402.py
blockrun_llm-0.3.6.dist-info/METADATA
blockrun_llm-0.3.6.dist-info/WHEEL
blockrun_llm-0.3.6.dist-info/licenses/LICENSE
blockrun_llm-0.3.6.dist-info/RECORD
