Metadata-Version: 2.4
Name: blockrun-llm
Version: 0.3.6
Summary: BlockRun SDK - Pay-per-request AI (LLM & Image) via x402 on Base
Project-URL: Homepage, https://blockrun.ai
Project-URL: Documentation, https://docs.blockrun.ai
Project-URL: Repository, https://github.com/BlockRunAI/blockrun-llm
Author-email: BlockRun <hello@blockrun.ai>
License-Expression: MIT
License-File: LICENSE
Keywords: ai,base,claude,dall-e,gemini,image-generation,llm,micropayments,nano-banana,openai,usdc,x402
Classifier: Development Status :: 4 - Beta
Classifier: Intended Audience :: Developers
Classifier: License :: OSI Approved :: MIT License
Classifier: Programming Language :: Python :: 3
Classifier: Programming Language :: Python :: 3.9
Classifier: Programming Language :: Python :: 3.10
Classifier: Programming Language :: Python :: 3.11
Classifier: Programming Language :: Python :: 3.12
Classifier: Topic :: Scientific/Engineering :: Artificial Intelligence
Requires-Python: >=3.9
Requires-Dist: eth-account>=0.11.0
Requires-Dist: httpx>=0.25.0
Requires-Dist: pydantic>=2.0.0
Requires-Dist: python-dotenv>=1.0.0
Requires-Dist: qrcode[pil]>=7.0
Provides-Extra: dev
Requires-Dist: black>=23.0.0; extra == 'dev'
Requires-Dist: mypy>=1.0.0; extra == 'dev'
Requires-Dist: pytest-asyncio>=0.21.0; extra == 'dev'
Requires-Dist: pytest>=7.0.0; extra == 'dev'
Requires-Dist: ruff>=0.1.0; extra == 'dev'
